comun_config.py
comun_config-0.7.dist-info/METADATA
comun_config-0.7.dist-info/WHEEL
comun_config-0.7.dist-info/top_level.txt
comun_config-0.7.dist-info/RECORD
