Metadata-Version: 2.1
Name: comun-config
Version: 0.7
Summary: UNKNOWN
Home-page: UNKNOWN
License: UNKNOWN
Platform: UNKNOWN
Requires-Dist: psycopg[binary]
